litesync/__init__.py
litesync/dbapi2.py
litesync-app/__init__.py
litesync-app/_sqlite3.cpython-38-darwin.so
litesync-app/dbapi2.py
litesync_app-0.0.1.dist-info/LICENSE
litesync_app-0.0.1.dist-info/METADATA
litesync_app-0.0.1.dist-info/WHEEL
litesync_app-0.0.1.dist-info/top_level.txt
litesync_app-0.0.1.dist-info/RECORD
