Metadata-Version: 2.1
Name: litesync-app
Version: 0.0.1
Summary: DB-API 2.0 interface for LiteSync
Home-page: https://gitlab.com/litesync/litesync-python3
Author: Bernardo Ramos
Author-email: contact@litesync.io
License: zlib/libpng
Platform: ALL
Classifier: Development Status :: 4 - Beta
Classifier: Intended Audience :: Developers
Classifier: License :: OSI Approved :: zlib/libpng License
Classifier: Operating System :: MacOS :: MacOS X
Classifier: Operating System :: Microsoft :: Windows
Classifier: Operating System :: POSIX
Classifier: Operating System :: Unix
Classifier: Operating System :: iOS
Classifier: Operating System :: Android
Classifier: Programming Language :: C
Classifier: Programming Language :: Python
Classifier: Topic :: Database :: Database Engines/Servers
Classifier: Topic :: Software Development :: Libraries :: Python Modules
